beep_notifications/__init__.py
beep_notifications/main.py
beep_notifications-0.2.2.dist-info/METADATA
beep_notifications-0.2.2.dist-info/WHEEL
beep_notifications-0.2.2.dist-info/top_level.txt
beep_notifications-0.2.2.dist-info/RECORD
