Metadata-Version: 2.1
Name: beep_notifications
Version: 0.2.2
Summary: Email notifications are a thing of the past, send notifications to messengers
Author: Daniel Baikalov
Author-email: felix.trof@gmail.com
